{
  "code": "0000",
  "data": [
    {
      "id": "121755_20012",
      "data_type": "school_score",
      "school_id": 951,
      "school_name": "重庆工商大学",
      "depart_id": 23046,
      "depart_name": "经济学院",
      "code": "020101",
      "name": "政治经济学",
      "politics": 40,
      "politics_str": "40",
      "english": 40,
      "english_str": "40",
      "special_one": 60,
      "special_one_str": "60",
      "special_two": 60,
      "special_two_str": "60",
      "total": 323,
      "note": "",
      "year": 2025,
      "degree_type": 2,
      "special_remark": "",
      "diff_total": 0,
      "diff_politics": 0,
      "diff_english": 0,
      "diff_special_one": 0,
      "diff_special_two": 0
    },
    {
      "id": "121756_20015",
      "data_type": "school_score",
      "school_id": 951,
      "school_name": "重庆工商大学",
      "depart_id": 23046,
      "depart_name": "经济学院",
      "code": "020104",
      "name": "西方经济学",
      "politics": 40,
      "politics_str": "40",
      "english": 40,
      "english_str": "40",
      "special_one": 60,
      "special_one_str": "60",
      "special_two": 60,
      "special_two_str": "60",
      "total": 323,
      "note": "",
      "year": 2025,
      "degree_type": 2,
      "special_remark": "",
      "diff_total": 0,
      "diff_politics": 0,
      "diff_english": 0,
      "diff_special_one": 0,
      "diff_special_two": 0
    },
    {
      "id": "121757_20017",
      "data_type": "school_score",
      "school_id": 951,
      "school_name": "重庆工商大学",
      "depart_id": 23046,
      "depart_name": "经济学院",
      "code": "020106",
      "name": "人口、资源与环境经济学",
      "politics": 40,
      "politics_str": "40",
      "english": 40,
      "english_str": "40",
      "special_one": 60,
      "special_one_str": "60",
      "special_two": 60,
      "special_two_str": "60",
      "total": 323,
      "note": "",
      "year": 2025,
      "degree_type": 2,
      "special_remark": "",
      "diff_total": 0,
      "diff_politics": 0,
      "diff_english": 0,
      "diff_special_one": 0,
      "diff_special_two": 0
    },
    {
      "id": "121748_20019",
      "data_type": "school_score",
      "school_id": 951,
      "school_name": "重庆工商大学",
      "depart_id": 34697,
      "depart_name": "成渝地区双城经济圈建设研究院",
      "code": "020201",
      "name": "国民经济学",
      "politics": 40,
      "politics_str": "40",
      "english": 40,
      "english_str": "40",
      "special_one": 60,
      "special_one_str": "60",
      "special_two": 60,
      "special_two_str": "60",
      "total": 323,
      "note": "",
      "year": 2025,
      "degree_type": 2,
      "special_remark": "",
      "diff_total": 0,
      "diff_politics": 0,
      "diff_english": 0,
      "diff_special_one": 0,
      "diff_special_two": 0
    },
    {
      "id": "121749_20020",
      "data_type": "school_score",
      "school_id": 951,
      "school_name": "重庆工商大学",
      "depart_id": 34697,
      "depart_name": "成渝地区双城经济圈建设研究院",
      "code": "020202",
      "name": "区域经济学",
      "politics": 40,
      "politics_str": "40",
      "english": 40,
      "english_str": "40",
      "special_one": 60,
      "special_one_str": "60",
      "special_two": 60,
      "special_two_str": "60",
      "total": 323,
      "note": "",
      "year": 2025,
      "degree_type": 2,
      "special_remark": "",
      "diff_total": 0,
      "diff_politics": 0,
      "diff_english": 0,
      "diff_special_one": 0,
      "diff_special_two": 0
    },
    {
      "id": "121758_20021",
      "data_type": "school_score",
      "school_id": 951,
      "school_name": "重庆工商大学",
      "depart_id": 23046,
      "depart_name": "经济学院",
      "code": "020203",
      "name": "财政学",
      "politics": 40,
      "politics_str": "40",
      "english": 40,
      "english_str": "40",
      "special_one": 60,
      "special_one_str": "60",
      "special_two": 60,
      "special_two_str": "60",
      "total": 323,
      "note": "",
      "year": 2025,
      "degree_type": 2,
      "special_remark": "",
      "diff_total": 0,
      "diff_politics": 0,
      "diff_english": 0,
      "diff_special_one": 0,
      "diff_special_two": 0
    },
    {
      "id": "121752_20022",
      "data_type": "school_score",
      "school_id": 951,
      "school_name": "重庆工商大学",
      "depart_id": 23055,
      "depart_name": "金融学院",
      "code": "020204",
      "name": "金融学",
      "politics": 40,
      "politics_str": "40",
      "english": 40,
      "english_str": "40",
      "special_one": 60,
      "special_one_str": "60",
      "special_two": 60,
      "special_two_str": "60",
      "total": 323,
      "note": "",
      "year": 2025,
      "degree_type": 2,
      "special_remark": "",
      "diff_total": 0,
      "diff_politics": 0,
      "diff_english": 0,
      "diff_special_one": 0,
      "diff_special_two": 0
    },
    {
      "id": "121759_20023",
      "data_type": "school_score",
      "school_id": 951,
      "school_name": "重庆工商大学",
      "depart_id": 23046,
      "depart_name": "经济学院",
      "code": "020205",
      "name": "产业经济学",
      "politics": 40,
      "politics_str": "40",
      "english": 40,
      "english_str": "40",
      "special_one": 60,
      "special_one_str": "60",
      "special_two": 60,
      "special_two_str": "60",
      "total": 323,
      "note": "",
      "year": 2025,
      "degree_type": 2,
      "special_remark": "",
      "diff_total": 0,
      "diff_politics": 0,
      "diff_english": 0,
      "diff_special_one": 0,
      "diff_special_two": 0
    },
    {
      "id": "121760_20024",
      "data_type": "school_score",
      "school_id": 951,
      "school_name": "重庆工商大学",
      "depart_id": 23046,
      "depart_name": "经济学院",
      "code": "020206",
      "name": "国际贸易学",
      "politics": 40,
      "politics_str": "40",
      "english": 40,
      "english_str": "40",
      "special_one": 60,
      "special_one_str": "60",
      "special_two": 60,
      "special_two_str": "60",
      "total": 323,
      "note": "",
      "year": 2025,
      "degree_type": 2,
      "special_remark": "",
      "diff_total": 0,
      "diff_politics": 0,
      "diff_english": 0,
      "diff_special_one": 0,
      "diff_special_two": 0
    },
    {
      "id": "121750_20027",
      "data_type": "school_score",
      "school_id": 951,
      "school_name": "重庆工商大学",
      "depart_id": 34697,
      "depart_name": "成渝地区双城经济圈建设研究院",
      "code": "020209",
      "name": "数量经济学",
      "politics": 40,
      "politics_str": "40",
      "english": 40,
      "english_str": "40",
      "special_one": 60,
      "special_one_str": "60",
      "special_two": 60,
      "special_two_str": "60",
      "total": 323,
      "note": "",
      "year": 2025,
      "degree_type": 2,
      "special_remark": "",
      "diff_total": 0,
      "diff_politics": 0,
      "diff_english": 0,
      "diff_special_one": 0,
      "diff_special_two": 0
    },
    {
      "id": "121753_20029",
      "data_type": "school_score",
      "school_id": 951,
      "school_name": "重庆工商大学",
      "depart_id": 23055,
      "depart_name": "金融学院",
      "code": "025100",
      "name": "金融",
      "politics": 40,
      "politics_str": "40",
      "english": 40,
      "english_str": "40",
      "special_one": 60,
      "special_one_str": "60",
      "special_two": 60,
      "special_two_str": "60",
      "total": 323,
      "note": "",
      "year": 2025,
      "degree_type": 1,
      "special_remark": "",
      "diff_total": 0,
      "diff_politics": 0,
      "diff_english": 0,
      "diff_special_one": 0,
      "diff_special_two": 0
    },
    {
      "id": "121762_20030",
      "data_type": "school_score",
      "school_id": 951,
      "school_name": "重庆工商大学",
      "depart_id": 23051,
      "depart_name": "数学与统计学院",
      "code": "025200",
      "name": "应用统计",
      "politics": 40,
      "politics_str": "40",
      "english": 40,
      "english_str": "40",
      "special_one": 60,
      "special_one_str": "60",
      "special_two": 60,
      "special_two_str": "60",
      "total": 323,
      "note": "",
      "year": 2025,
      "degree_type": 1,
      "special_remark": "",
      "diff_total": 0,
      "diff_politics": 0,
      "diff_english": 0,
      "diff_special_one": 0,
      "diff_special_two": 0
    },
    {
      "id": "121751_20032",
      "data_type": "school_score",
      "school_id": 951,
      "school_name": "重庆工商大学",
      "depart_id": 23047,
      "depart_name": "工商管理学院",
      "code": "025400",
      "name": "国际商务",
      "politics": 40,
      "politics_str": "40",
      "english": 40,
      "english_str": "40",
      "special_one": 60,
      "special_one_str": "60",
      "special_two": 60,
      "special_two_str": "60",
      "total": 323,
      "note": "",
      "year": 2025,
      "degree_type": 1,
      "special_remark": "",
      "diff_total": 0,
      "diff_politics": 0,
      "diff_english": 0,
      "diff_special_one": 0,
      "diff_special_two": 0
    },
    {
      "id": "121754_20033",
      "data_type": "school_score",
      "school_id": 951,
      "school_name": "重庆工商大学",
      "depart_id": 23055,
      "depart_name": "金融学院",
      "code": "025500",
      "name": "保险",
      "politics": 40,
      "politics_str": "40",
      "english": 40,
      "english_str": "40",
      "special_one": 60,
      "special_one_str": "60",
      "special_two": 60,
      "special_two_str": "60",
      "total": 323,
      "note": "",
      "year": 2025,
      "degree_type": 1,
      "special_remark": "",
      "diff_total": 0,
      "diff_politics": 0,
      "diff_english": 0,
      "diff_special_one": 0,
      "diff_special_two": 0
    },
    {
      "id": "121761_20035",
      "data_type": "school_score",
      "school_id": 951,
      "school_name": "重庆工商大学",
      "depart_id": 23046,
      "depart_name": "经济学院",
      "code": "025800",
      "name": "数字经济",
      "politics": 40,
      "politics_str": "40",
      "english": 40,
      "english_str": "40",
      "special_one": 60,
      "special_one_str": "60",
      "special_two": 60,
      "special_two_str": "60",
      "total": 323,
      "note": "",
      "year": 2025,
      "degree_type": 1,
      "special_remark": "",
      "diff_total": 0,
      "diff_politics": 0,
      "diff_english": 0,
      "diff_special_one": 0,
      "diff_special_two": 0
    },
    {
      "id": 153016,
      "data_type": "score_level",
      "school_id": 951,
      "school_name": "重庆工商大学",
      "depart_id": 0,
      "depart_name": "不区分院系",
      "code": "0253",
      "name": "税务",
      "politics": 40,
      "politics_str": "40",
      "english": 40,
      "english_str": "40",
      "special_one": 60,
      "special_one_str": "60",
      "special_two": 60,
      "special_two_str": "60",
      "total": 342,
      "note": "",
      "year": 2025,
      "degree_type": 1,
      "special_remark": "",
      "diff_total": 19,
      "diff_politics": 0,
      "diff_english": 0,
      "diff_special_one": 0,
      "diff_special_two": 0
    },
    {
      "id": "121763_20058",
      "data_type": "school_score",
      "school_id": 951,
      "school_name": "重庆工商大学",
      "depart_id": 23058,
      "depart_name": "法学与社会学学院",
      "code": "030301",
      "name": "社会学",
      "politics": 40,
      "politics_str": "40",
      "english": 40,
      "english_str": "40",
      "special_one": 60,
      "special_one_str": "60",
      "special_two": 60,
      "special_two_str": "60",
      "total": 350,
      "note": "",
      "year": 2025,
      "degree_type": 2,
      "special_remark": "",
      "diff_total": 27,
      "diff_politics": 0,
      "diff_english": 0,
      "diff_special_one": 0,
      "diff_special_two": 0
    },
    {
      "id": "121764_20059",
      "data_type": "school_score",
      "school_id": 951,
      "school_name": "重庆工商大学",
      "depart_id": 23058,
      "depart_name": "法学与社会学学院",
      "code": "030302",
      "name": "人口学",
      "politics": 40,
      "politics_str": "40",
      "english": 40,
      "english_str": "40",
      "special_one": 60,
      "special_one_str": "60",
      "special_two": 60,
      "special_two_str": "60",
      "total": 323,
      "note": "",
      "year": 2025,
      "degree_type": 2,
      "special_remark": "",
      "diff_total": 0,
      "diff_politics": 0,
      "diff_english": 0,
      "diff_special_one": 0,
      "diff_special_two": 0
    },
    {
      "id": "121765_20061",
      "data_type": "school_score",
      "school_id": 951,
      "school_name": "重庆工商大学",
      "depart_id": 23058,
      "depart_name": "法学与社会学学院",
      "code": "030304",
      "name": "民俗学",
      "politics": 40,
      "politics_str": "40",
      "english": 40,
      "english_str": "40",
      "special_one": 60,
      "special_one_str": "60",
      "special_two": 60,
      "special_two_str": "60",
      "total": 323,
      "note": "",
      "year": 2025,
      "degree_type": 2,
      "special_remark": "",
      "diff_total": 0,
      "diff_politics": 0,
      "diff_english": 0,
      "diff_special_one": 0,
      "diff_special_two": 0
    },
    {
      "id": "121769_20069",
      "data_type": "school_score",
      "school_id": 951,
      "school_name": "重庆工商大学",
      "depart_id": 27369,
      "depart_name": "马克思主义学院",
      "code": "030501",
      "name": "马克思主义基本原理",
      "politics": 40,
      "politics_str": "40",
      "english": 40,
      "english_str": "40",
      "special_one": 60,
      "special_one_str": "60",
      "special_two": 60,
      "special_two_str": "60",
      "total": 323,
      "note": "",
      "year": 2025,
      "degree_type": 2,
      "special_remark": "",
      "diff_total": 0,
      "diff_politics": 0,
      "diff_english": 0,
      "diff_special_one": 0,
      "diff_special_two": 0
    },
    {
      "id": "121770_20071",
      "data_type": "school_score",
      "school_id": 951,
      "school_name": "重庆工商大学",
      "depart_id": 27369,
      "depart_name": "马克思主义学院",
      "code": "030503",
      "name": "马克思主义中国化研究",
      "politics": 40,
      "politics_str": "40",
      "english": 40,
      "english_str": "40",
      "special_one": 60,
      "special_one_str": "60",
      "special_two": 60,
      "special_two_str": "60",
      "total": 323,
      "note": "",
      "year": 2025,
      "degree_type": 2,
      "special_remark": "",
      "diff_total": 0,
      "diff_politics": 0,
      "diff_english": 0,
      "diff_special_one": 0,
      "diff_special_two": 0
    },
    {
      "id": "121771_20073",
      "data_type": "school_score",
      "school_id": 951,
      "school_name": "重庆工商大学",
      "depart_id": 27369,
      "depart_name": "马克思主义学院",
      "code": "030505",
      "name": "思想政治教育",
      "politics": 40,
      "politics_str": "40",
      "english": 40,
      "english_str": "40",
      "special_one": 60,
      "special_one_str": "60",
      "special_two": 60,
      "special_two_str": "60",
      "total": 323,
      "note": "",
      "year": 2025,
      "degree_type": 2,
      "special_remark": "",
      "diff_total": 0,
      "diff_politics": 0,
      "diff_english": 0,
      "diff_special_one": 0,
      "diff_special_two": 0
    },
    {
      "id": "121772_20074",
      "data_type": "school_score",
      "school_id": 951,
      "school_name": "重庆工商大学",
      "depart_id": 27369,
      "depart_name": "马克思主义学院",
      "code": "030506",
      "name": "中国近现代史基本问题研究",
      "politics": 40,
      "politics_str": "40",
      "english": 40,
      "english_str": "40",
      "special_one": 60,
      "special_one_str": "60",
      "special_two": 60,
      "special_two_str": "60",
      "total": 323,
      "note": "",
      "year": 2025,
      "degree_type": 2,
      "special_remark": "",
      "diff_total": 0,
      "diff_politics": 0,
      "diff_english": 0,
      "diff_special_one": 0,
      "diff_special_two": 0
    },
    {
      "id": "121773_20959",
      "data_type": "school_score",
      "school_id": 951,
      "school_name": "重庆工商大学",
      "depart_id": 27369,
      "depart_name": "马克思主义学院",
      "code": "0305Z1",
      "name": "党的建设",
      "politics": 40,
      "politics_str": "40",
      "english": 40,
      "english_str": "40",
      "special_one": 60,
      "special_one_str": "60",
      "special_two": 60,
      "special_two_str": "60",
      "total": 323,
      "note": "",
      "year": 2025,
      "degree_type": 2,
      "special_remark": "",
      "diff_total": 0,
      "diff_politics": 0,
      "diff_english": 0,
      "diff_special_one": 0,
      "diff_special_two": 0
    },
    {
      "id": "121766_20079",
      "data_type": "school_score",
      "school_id": 951,
      "school_name": "重庆工商大学",
      "depart_id": 23058,
      "depart_name": "法学与社会学学院",
      "code": "035101",
      "name": "法律（非法学）",
      "politics": 40,
      "politics_str": "40",
      "english": 40,
      "english_str": "40",
      "special_one": 60,
      "special_one_str": "60",
      "special_two": 60,
      "special_two_str": "60",
      "total": 323,
      "note": "",
      "year": 2025,
      "degree_type": 1,
      "special_remark": "",
      "diff_total": 0,
      "diff_politics": 0,
      "diff_english": 0,
      "diff_special_one": 0,
      "diff_special_two": 0
    },
    {
      "id": "121767_20080",
      "data_type": "school_score",
      "school_id": 951,
      "school_name": "重庆工商大学",
      "depart_id": 23058,
      "depart_name": "法学与社会学学院",
      "code": "035102",
      "name": "法律（法学）",
      "politics": 40,
      "politics_str": "40",
      "english": 40,
      "english_str": "40",
      "special_one": 60,
      "special_one_str": "60",
      "special_two": 60,
      "special_two_str": "60",
      "total": 323,
      "note": "",
      "year": 2025,
      "degree_type": 1,
      "special_remark": "",
      "diff_total": 0,
      "diff_politics": 0,
      "diff_english": 0,
      "diff_special_one": 0,
      "diff_special_two": 0
    },
    {
      "id": "121768_20083",
      "data_type": "school_score",
      "school_id": 951,
      "school_name": "重庆工商大学",
      "depart_id": 23058,
      "depart_name": "法学与社会学学院",
      "code": "035400",
      "name": "知识产权",
      "politics": 40,
      "politics_str": "40",
      "english": 40,
      "english_str": "40",
      "special_one": 60,
      "special_one_str": "60",
      "special_two": 60,
      "special_two_str": "60",
      "total": 323,
      "note": "",
      "year": 2025,
      "degree_type": 1,
      "special_remark": "",
      "diff_total": 0,
      "diff_politics": 0,
      "diff_english": 0,
      "diff_special_one": 0,
      "diff_special_two": 0
    },
    {
      "id": 153017,
      "data_type": "score_level",
      "school_id": 951,
      "school_name": "重庆工商大学",
      "depart_id": 0,
      "depart_name": "不区分院系",
      "code": "0352",
      "name": "社会工作",
      "politics": 40,
      "politics_str": "40",
      "english": 40,
      "english_str": "40",
      "special_one": 60,
      "special_one_str": "60",
      "special_two": 60,
      "special_two_str": "60",
      "total": 333,
      "note": "",
      "year": 2025,
      "degree_type": 1,
      "special_remark": "",
      "diff_total": 10,
      "diff_politics": 0,
      "diff_english": 0,
      "diff_special_one": 0,
      "diff_special_two": 0
    },
    {
      "id": 153018,
      "data_type": "score_level",
      "school_id": 951,
      "school_name": "重庆工商大学",
      "depart_id": 0,
      "depart_name": "不区分院系",
      "code": "0452",
      "name": "体育",
      "politics": 36,
      "politics_str": "36",
      "english": 36,
      "english_str": "36",
      "special_one": 108,
      "special_one_str": "108",
      "special_two": 108,
      "special_two_str": "108",
      "total": 304,
      "note": "",
      "year": 2025,
      "degree_type": 1,
      "special_remark": "",
      "diff_total": 0,
      "diff_politics": 0,
      "diff_english": 0,
      "diff_special_one": 0,
      "diff_special_two": 0
    },
    {
      "id": "121775_20159",
      "data_type": "school_score",
      "school_id": 951,
      "school_name": "重庆工商大学",
      "depart_id": 23049,
      "depart_name": "文学与新闻学院",
      "code": "050301",
      "name": "新闻学",
      "politics": 47,
      "politics_str": "47",
      "english": 47,
      "english_str": "47",
      "special_one": 71,
      "special_one_str": "71",
      "special_two": 71,
      "special_two_str": "71",
      "total": 351,
      "note": "",
      "year": 2025,
      "degree_type": 2,
      "special_remark": "",
      "diff_total": 0,
      "diff_politics": 0,
      "diff_english": 0,
      "diff_special_one": 0,
      "diff_special_two": 0
    },
    {
      "id": "121776_20160",
      "data_type": "school_score",
      "school_id": 951,
      "school_name": "重庆工商大学",
      "depart_id": 23049,
      "depart_name": "文学与新闻学院",
      "code": "050302",
      "name": "传播学",
      "politics": 47,
      "politics_str": "47",
      "english": 47,
      "english_str": "47",
      "special_one": 71,
      "special_one_str": "71",
      "special_two": 71,
      "special_two_str": "71",
      "total": 351,
      "note": "",
      "year": 2025,
      "degree_type": 2,
      "special_remark": "",
      "diff_total": 0,
      "diff_politics": 0,
      "diff_english": 0,
      "diff_special_one": 0,
      "diff_special_two": 0
    },
    {
      "id": "121777_21104",
      "data_type": "school_score",
      "school_id": 951,
      "school_name": "重庆工商大学",
      "depart_id": 23049,
      "depart_name": "文学与新闻学院",
      "code": "0503Z1",
      "name": "广告学",
      "politics": 47,
      "politics_str": "47",
      "english": 47,
      "english_str": "47",
      "special_one": 71,
      "special_one_str": "71",
      "special_two": 71,
      "special_two_str": "71",
      "total": 351,
      "note": "",
      "year": 2025,
      "degree_type": 2,
      "special_remark": "",
      "diff_total": 0,
      "diff_politics": 0,
      "diff_english": 0,
      "diff_special_one": 0,
      "diff_special_two": 0
    },
    {
      "id": "121778_21108",
      "data_type": "school_score",
      "school_id": 951,
      "school_name": "重庆工商大学",
      "depart_id": 23049,
      "depart_name": "文学与新闻学院",
      "code": "0503Z2",
      "name": "传媒经济学",
      "politics": 47,
      "politics_str": "47",
      "english": 47,
      "english_str": "47",
      "special_one": 71,
      "special_one_str": "71",
      "special_two": 71,
      "special_two_str": "71",
      "total": 351,
      "note": "",
      "year": 2025,
      "degree_type": 2,
      "special_remark": "",
      "diff_total": 0,
      "diff_politics": 0,
      "diff_english": 0,
      "diff_special_one": 0,
      "diff_special_two": 0
    },
    {
      "id": "121774_20162",
      "data_type": "school_score",
      "school_id": 951,
      "school_name": "重庆工商大学",
      "depart_id": 23062,
      "depart_name": "外国语学院",
      "code": "055101",
      "name": "英语笔译",
      "politics": 47,
      "politics_str": "47",
      "english": 47,
      "english_str": "47",
      "special_one": 71,
      "special_one_str": "71",
      "special_two": 71,
      "special_two_str": "71",
      "total": 351,
      "note": "",
      "year": 2025,
      "degree_type": 1,
      "special_remark": "",
      "diff_total": 0,
      "diff_politics": 0,
      "diff_english": 0,
      "diff_special_one": 0,
      "diff_special_two": 0
    },
    {
      "id": 153019,
      "data_type": "score_level",
      "school_id": 951,
      "school_name": "重庆工商大学",
      "depart_id": 0,
      "depart_name": "不区分院系",
      "code": "0552",
      "name": "新闻与传播",
      "politics": 47,
      "politics_str": "47",
      "english": 47,
      "english_str": "47",
      "special_one": 71,
      "special_one_str": "71",
      "special_two": 71,
      "special_two_str": "71",
      "total": 389,
      "note": "",
      "year": 2025,
      "degree_type": 1,
      "special_remark": "",
      "diff_total": 38,
      "diff_politics": 0,
      "diff_english": 0,
      "diff_special_one": 0,
      "diff_special_two": 0
    },
    {
      "id": "121779_20195",
      "data_type": "school_score",
      "school_id": 951,
      "school_name": "重庆工商大学",
      "depart_id": 23051,
      "depart_name": "数学与统计学院",
      "code": "070100",
      "name": "数学",
      "politics": 34,
      "politics_str": "34",
      "english": 34,
      "english_str": "34",
      "special_one": 51,
      "special_one_str": "51",
      "special_two": 51,
      "special_two_str": "51",
      "total": 274,
      "note": "",
      "year": 2025,
      "degree_type": 2,
      "special_remark": "",
      "diff_total": 0,
      "diff_politics": 0,
      "diff_english": 0,
      "diff_special_one": 0,
      "diff_special_two": 0
    },
    {
      "id": "121780_20257",
      "data_type": "school_score",
      "school_id": 951,
      "school_name": "重庆工商大学",
      "depart_id": 23051,
      "depart_name": "数学与统计学院",
      "code": "071400",
      "name": "统计学",
      "politics": 34,
      "politics_str": "34",
      "english": 34,
      "english_str": "34",
      "special_one": 51,
      "special_one_str": "51",
      "special_two": 51,
      "special_two_str": "51",
      "total": 274,
      "note": "",
      "year": 2025,
      "degree_type": 2,
      "special_remark": "",
      "diff_total": 0,
      "diff_politics": 0,
      "diff_english": 0,
      "diff_special_one": 0,
      "diff_special_two": 0
    },
    {
      "id": "121787_20321",
      "data_type": "school_score",
      "school_id": 951,
      "school_name": "重庆工商大学",
      "depart_id": 23050,
      "depart_name": "机械工程学院",
      "code": "080201",
      "name": "机械制造及其自动化",
      "politics": 34,
      "politics_str": "34",
      "english": 34,
      "english_str": "34",
      "special_one": 51,
      "special_one_str": "51",
      "special_two": 51,
      "special_two_str": "51",
      "total": 260,
      "note": "",
      "year": 2025,
      "degree_type": 2,
      "special_remark": "",
      "diff_total": 0,
      "diff_politics": 0,
      "diff_english": 0,
      "diff_special_one": 0,
      "diff_special_two": 0
    },
    {
      "id": "121788_20322",
      "data_type": "school_score",
      "school_id": 951,
      "school_name": "重庆工商大学",
      "depart_id": 23050,
      "depart_name": "机械工程学院",
      "code": "080202",
      "name": "机械电子工程",
      "politics": 34,
      "politics_str": "34",
      "english": 34,
      "english_str": "34",
      "special_one": 51,
      "special_one_str": "51",
      "special_two": 51,
      "special_two_str": "51",
      "total": 260,
      "note": "",
      "year": 2025,
      "degree_type": 2,
      "special_remark": "",
      "diff_total": 0,
      "diff_politics": 0,
      "diff_english": 0,
      "diff_special_one": 0,
      "diff_special_two": 0
    },
    {
      "id": "121789_20323",
      "data_type": "school_score",
      "school_id": 951,
      "school_name": "重庆工商大学",
      "depart_id": 23050,
      "depart_name": "机械工程学院",
      "code": "080203",
      "name": "机械设计及理论",
      "politics": 34,
      "politics_str": "34",
      "english": 34,
      "english_str": "34",
      "special_one": 51,
      "special_one_str": "51",
      "special_two": 51,
      "special_two_str": "51",
      "total": 260,
      "note": "",
      "year": 2025,
      "degree_type": 2,
      "special_remark": "",
      "diff_total": 0,
      "diff_politics": 0,
      "diff_english": 0,
      "diff_special_one": 0,
      "diff_special_two": 0
    },
    {
      "id": "121782_20451",
      "data_type": "school_score",
      "school_id": 951,
      "school_name": "重庆工商大学",
      "depart_id": 23060,
      "depart_name": "环境与资源学院",
      "code": "083001",
      "name": "环境科学",
      "politics": 34,
      "politics_str": "34",
      "english": 34,
      "english_str": "34",
      "special_one": 51,
      "special_one_str": "51",
      "special_two": 51,
      "special_two_str": "51",
      "total": 260,
      "note": "",
      "year": 2025,
      "degree_type": 2,
      "special_remark": "",
      "diff_total": 0,
      "diff_politics": 0,
      "diff_english": 0,
      "diff_special_one": 0,
      "diff_special_two": 0
    },
    {
      "id": "121783_20452",
      "data_type": "school_score",
      "school_id": 951,
      "school_name": "重庆工商大学",
      "depart_id": 23060,
      "depart_name": "环境与资源学院",
      "code": "083002",
      "name": "环境工程",
      "politics": 34,
      "politics_str": "34",
      "english": 34,
      "english_str": "34",
      "special_one": 51,
      "special_one_str": "51",
      "special_two": 51,
      "special_two_str": "51",
      "total": 260,
      "note": "",
      "year": 2025,
      "degree_type": 2,
      "special_remark": "",
      "diff_total": 0,
      "diff_politics": 0,
      "diff_english": 0,
      "diff_special_one": 0,
      "diff_special_two": 0
    },
    {
      "id": "121781_21508",
      "data_type": "school_score",
      "school_id": 951,
      "school_name": "重庆工商大学",
      "depart_id": 26408,
      "depart_name": "废油资源化技术与装备教育部工程研究中心",
      "code": "0830Z1",
      "name": "环境保护技术及装备",
      "politics": 34,
      "politics_str": "34",
      "english": 34,
      "english_str": "34",
      "special_one": 51,
      "special_one_str": "51",
      "special_two": 51,
      "special_two_str": "51",
      "total": 260,
      "note": "",
      "year": 2025,
      "degree_type": 2,
      "special_remark": "",
      "diff_total": 0,
      "diff_politics": 0,
      "diff_english": 0,
      "diff_special_one": 0,
      "diff_special_two": 0
    },
    {
      "id": "121795_20455",
      "data_type": "school_score",
      "school_id": 951,
      "school_name": "重庆工商大学",
      "depart_id": 34698,
      "depart_name": "食品科学与工程学院",
      "code": "083201",
      "name": "食品科学",
      "politics": 34,
      "politics_str": "34",
      "english": 34,
      "english_str": "34",
      "special_one": 51,
      "special_one_str": "51",
      "special_two": 51,
      "special_two_str": "51",
      "total": 260,
      "note": "",
      "year": 2025,
      "degree_type": 2,
      "special_remark": "",
      "diff_total": 0,
      "diff_politics": 0,
      "diff_english": 0,
      "diff_special_one": 0,
      "diff_special_two": 0
    },
    {
      "id": "121796_20457",
      "data_type": "school_score",
      "school_id": 951,
      "school_name": "重庆工商大学",
      "depart_id": 34698,
      "depart_name": "食品科学与工程学院",
      "code": "083203",
      "name": "农产品加工及贮藏工程",
      "politics": 34,
      "politics_str": "34",
      "english": 34,
      "english_str": "34",
      "special_one": 51,
      "special_one_str": "51",
      "special_two": 51,
      "special_two_str": "51",
      "total": 260,
      "note": "",
      "year": 2025,
      "degree_type": 2,
      "special_remark": "",
      "diff_total": 0,
      "diff_politics": 0,
      "diff_english": 0,
      "diff_special_one": 0,
      "diff_special_two": 0
    },
    {
      "id": "121791_20460",
      "data_type": "school_score",
      "school_id": 951,
      "school_name": "重庆工商大学",
      "depart_id": 27370,
      "depart_name": "人工智能学院",
      "code": "083500",
      "name": "软件工程",
      "politics": 34,
      "politics_str": "34",
      "english": 34,
      "english_str": "34",
      "special_one": 51,
      "special_one_str": "51",
      "special_two": 51,
      "special_two_str": "51",
      "total": 260,
      "note": "",
      "year": 2025,
      "degree_type": 2,
      "special_remark": "",
      "diff_total": 0,
      "diff_politics": 0,
      "diff_english": 0,
      "diff_special_one": 0,
      "diff_special_two": 0
    },
    {
      "id": "121792_20468",
      "data_type": "school_score",
      "school_id": 951,
      "school_name": "重庆工商大学",
      "depart_id": 27370,
      "depart_name": "人工智能学院",
      "code": "085401",
      "name": "新一代电子信息技术（含量子技术等）",
      "politics": 34,
      "politics_str": "34",
      "english": 34,
      "english_str": "34",
      "special_one": 51,
      "special_one_str": "51",
      "special_two": 51,
      "special_two_str": "51",
      "total": 260,
      "note": "",
      "year": 2025,
      "degree_type": 1,
      "special_remark": "",
      "diff_total": 0,
      "diff_politics": 0,
      "diff_english": 0,
      "diff_special_one": 0,
      "diff_special_two": 0
    },
    {
      "id": "121793_20471",
      "data_type": "school_score",
      "school_id": 951,
      "school_name": "重庆工商大学",
      "depart_id": 27370,
      "depart_name": "人工智能学院",
      "code": "085404",
      "name": "计算机技术",
      "politics": 34,
      "politics_str": "34",
      "english": 34,
      "english_str": "34",
      "special_one": 51,
      "special_one_str": "51",
      "special_two": 51,
      "special_two_str": "51",
      "total": 260,
      "note": "",
      "year": 2025,
      "degree_type": 1,
      "special_remark": "",
      "diff_total": 0,
      "diff_politics": 0,
      "diff_english": 0,
      "diff_special_one": 0,
      "diff_special_two": 0
    },
    {
      "id": "121794_20477",
      "data_type": "school_score",
      "school_id": 951,
      "school_name": "重庆工商大学",
      "depart_id": 27370,
      "depart_name": "人工智能学院",
      "code": "085410",
      "name": "人工智能",
      "politics": 34,
      "politics_str": "34",
      "english": 34,
      "english_str": "34",
      "special_one": 51,
      "special_one_str": "51",
      "special_two": 51,
      "special_two_str": "51",
      "total": 260,
      "note": "",
      "year": 2025,
      "degree_type": 1,
      "special_remark": "",
      "diff_total": 0,
      "diff_politics": 0,
      "diff_english": 0,
      "diff_special_one": 0,
      "diff_special_two": 0
    },
    {
      "id": "121790_20480",
      "data_type": "school_score",
      "school_id": 951,
      "school_name": "重庆工商大学",
      "depart_id": 23050,
      "depart_name": "机械工程学院",
      "code": "085500",
      "name": "机械",
      "politics": 34,
      "politics_str": "34",
      "english": 34,
      "english_str": "34",
      "special_one": 51,
      "special_one_str": "51",
      "special_two": 51,
      "special_two_str": "51",
      "total": 260,
      "note": "",
      "year": 2025,
      "degree_type": 1,
      "special_remark": "",
      "diff_total": 0,
      "diff_politics": 0,
      "diff_english": 0,
      "diff_special_one": 0,
      "diff_special_two": 0
    },
    {
      "id": "121784_20492",
      "data_type": "school_score",
      "school_id": 951,
      "school_name": "重庆工商大学",
      "depart_id": 23060,
      "depart_name": "环境与资源学院",
      "code": "085601",
      "name": "材料工程",
      "politics": 34,
      "politics_str": "34",
      "english": 34,
      "english_str": "34",
      "special_one": 51,
      "special_one_str": "51",
      "special_two": 51,
      "special_two_str": "51",
      "total": 260,
      "note": "",
      "year": 2025,
      "degree_type": 1,
      "special_remark": "",
      "diff_total": 0,
      "diff_politics": 0,
      "diff_english": 0,
      "diff_special_one": 0,
      "diff_special_two": 0
    },
    {
      "id": "121785_20493",
      "data_type": "school_score",
      "school_id": 951,
      "school_name": "重庆工商大学",
      "depart_id": 23060,
      "depart_name": "环境与资源学院",
      "code": "085602",
      "name": "化学工程",
      "politics": 34,
      "politics_str": "34",
      "english": 34,
      "english_str": "34",
      "special_one": 51,
      "special_one_str": "51",
      "special_two": 51,
      "special_two_str": "51",
      "total": 260,
      "note": "",
      "year": 2025,
      "degree_type": 1,
      "special_remark": "",
      "diff_total": 0,
      "diff_politics": 0,
      "diff_english": 0,
      "diff_special_one": 0,
      "diff_special_two": 0
    },
    {
      "id": "121786_20499",
      "data_type": "school_score",
      "school_id": 951,
      "school_name": "重庆工商大学",
      "depart_id": 23060,
      "depart_name": "环境与资源学院",
      "code": "085701",
      "name": "环境工程",
      "politics": 34,
      "politics_str": "34",
      "english": 34,
      "english_str": "34",
      "special_one": 51,
      "special_one_str": "51",
      "special_two": 51,
      "special_two_str": "51",
      "total": 260,
      "note": "",
      "year": 2025,
      "degree_type": 1,
      "special_remark": "",
      "diff_total": 0,
      "diff_politics": 0,
      "diff_english": 0,
      "diff_special_one": 0,
      "diff_special_two": 0
    },
    {
      "id": "121797_20522",
      "data_type": "school_score",
      "school_id": 951,
      "school_name": "重庆工商大学",
      "depart_id": 34698,
      "depart_name": "食品科学与工程学院",
      "code": "086001",
      "name": "生物技术与工程",
      "politics": 34,
      "politics_str": "34",
      "english": 34,
      "english_str": "34",
      "special_one": 51,
      "special_one_str": "51",
      "special_two": 51,
      "special_two_str": "51",
      "total": 260,
      "note": "",
      "year": 2025,
      "degree_type": 1,
      "special_remark": "",
      "diff_total": 0,
      "diff_politics": 0,
      "diff_english": 0,
      "diff_special_one": 0,
      "diff_special_two": 0
    },
    {
      "id": "121798_20523",
      "data_type": "school_score",
      "school_id": 951,
      "school_name": "重庆工商大学",
      "depart_id": 34698,
      "depart_name": "食品科学与工程学院",
      "code": "086002",
      "name": "制药工程",
      "politics": 34,
      "politics_str": "34",
      "english": 34,
      "english_str": "34",
      "special_one": 51,
      "special_one_str": "51",
      "special_two": 51,
      "special_two_str": "51",
      "total": 260,
      "note": "",
      "year": 2025,
      "degree_type": 1,
      "special_remark": "",
      "diff_total": 0,
      "diff_politics": 0,
      "diff_english": 0,
      "diff_special_one": 0,
      "diff_special_two": 0
    },
    {
      "id": "121799_20524",
      "data_type": "school_score",
      "school_id": 951,
      "school_name": "重庆工商大学",
      "depart_id": 34698,
      "depart_name": "食品科学与工程学院",
      "code": "086003",
      "name": "食品工程",
      "politics": 34,
      "politics_str": "34",
      "english": 34,
      "english_str": "34",
      "special_one": 51,
      "special_one_str": "51",
      "special_two": 51,
      "special_two_str": "51",
      "total": 260,
      "note": "",
      "year": 2025,
      "degree_type": 1,
      "special_remark": "",
      "diff_total": 0,
      "diff_politics": 0,
      "diff_english": 0,
      "diff_special_one": 0,
      "diff_special_two": 0
    },
    {
      "id": "121800_20525",
      "data_type": "school_score",
      "school_id": 951,
      "school_name": "重庆工商大学",
      "depart_id": 34698,
      "depart_name": "食品科学与工程学院",
      "code": "086004",
      "name": "发酵工程",
      "politics": 34,
      "politics_str": "34",
      "english": 34,
      "english_str": "34",
      "special_one": 51,
      "special_one_str": "51",
      "special_two": 51,
      "special_two_str": "51",
      "total": 260,
      "note": "",
      "year": 2025,
      "degree_type": 1,
      "special_remark": "",
      "diff_total": 0,
      "diff_politics": 0,
      "diff_english": 0,
      "diff_special_one": 0,
      "diff_special_two": 0
    },
    {
      "id": 153020,
      "data_type": "score_level",
      "school_id": 951,
      "school_name": "重庆工商大学",
      "depart_id": 0,
      "depart_name": "不区分院系",
      "code": "0833",
      "name": "城乡规划学",
      "politics": 34,
      "politics_str": "34",
      "english": 34,
      "english_str": "34",
      "special_one": 51,
      "special_one_str": "51",
      "special_two": 51,
      "special_two_str": "51",
      "total": 296,
      "note": "",
      "year": 2025,
      "degree_type": 2,
      "special_remark": "",
      "diff_total": 36,
      "diff_politics": 0,
      "diff_english": 0,
      "diff_special_one": 0,
      "diff_special_two": 0
    },
    {
      "id": "121805_20729",
      "data_type": "school_score",
      "school_id": 951,
      "school_name": "重庆工商大学",
      "depart_id": 23048,
      "depart_name": "管理科学与工程学院",
      "code": "120100",
      "name": "管理科学与工程",
      "politics": 41,
      "politics_str": "41",
      "english": 41,
      "english_str": "41",
      "special_one": 62,
      "special_one_str": "62",
      "special_two": 62,
      "special_two_str": "62",
      "total": 333,
      "note": "",
      "year": 2025,
      "degree_type": 2,
      "special_remark": "",
      "diff_total": 0,
      "diff_politics": 0,
      "diff_english": 0,
      "diff_special_one": 0,
      "diff_special_two": 0
    },
    {
      "id": "121806_20731",
      "data_type": "school_score",
      "school_id": 951,
      "school_name": "重庆工商大学",
      "depart_id": 23056,
      "depart_name": "会计学院",
      "code": "120201",
      "name": "会计学",
      "politics": 41,
      "politics_str": "41",
      "english": 41,
      "english_str": "41",
      "special_one": 62,
      "special_one_str": "62",
      "special_two": 62,
      "special_two_str": "62",
      "total": 333,
      "note": "",
      "year": 2025,
      "degree_type": 2,
      "special_remark": "",
      "diff_total": 0,
      "diff_politics": 0,
      "diff_english": 0,
      "diff_special_one": 0,
      "diff_special_two": 0
    },
    {
      "id": "121801_20732",
      "data_type": "school_score",
      "school_id": 951,
      "school_name": "重庆工商大学",
      "depart_id": 23047,
      "depart_name": "工商管理学院",
      "code": "120202",
      "name": "企业管理",
      "politics": 41,
      "politics_str": "41",
      "english": 41,
      "english_str": "41",
      "special_one": 62,
      "special_one_str": "62",
      "special_two": 62,
      "special_two_str": "62",
      "total": 333,
      "note": "",
      "year": 2025,
      "degree_type": 2,
      "special_remark": "",
      "diff_total": 0,
      "diff_politics": 0,
      "diff_english": 0,
      "diff_special_one": 0,
      "diff_special_two": 0
    },
    {
      "id": "121802_20733",
      "data_type": "school_score",
      "school_id": 951,
      "school_name": "重庆工商大学",
      "depart_id": 23047,
      "depart_name": "工商管理学院",
      "code": "120203",
      "name": "旅游管理",
      "politics": 41,
      "politics_str": "41",
      "english": 41,
      "english_str": "41",
      "special_one": 62,
      "special_one_str": "62",
      "special_two": 62,
      "special_two_str": "62",
      "total": 333,
      "note": "",
      "year": 2025,
      "degree_type": 2,
      "special_remark": "",
      "diff_total": 0,
      "diff_politics": 0,
      "diff_english": 0,
      "diff_special_one": 0,
      "diff_special_two": 0
    },
    {
      "id": "121803_20734",
      "data_type": "school_score",
      "school_id": 951,
      "school_name": "重庆工商大学",
      "depart_id": 23047,
      "depart_name": "工商管理学院",
      "code": "120204",
      "name": "技术经济及管理",
      "politics": 41,
      "politics_str": "41",
      "english": 41,
      "english_str": "41",
      "special_one": 62,
      "special_one_str": "62",
      "special_two": 62,
      "special_two_str": "62",
      "total": 333,
      "note": "",
      "year": 2025,
      "degree_type": 2,
      "special_remark": "",
      "diff_total": 0,
      "diff_politics": 0,
      "diff_english": 0,
      "diff_special_one": 0,
      "diff_special_two": 0
    },
    {
      "id": "121804_22029",
      "data_type": "school_score",
      "school_id": 951,
      "school_name": "重庆工商大学",
      "depart_id": 23047,
      "depart_name": "工商管理学院",
      "code": "1202Z1",
      "name": "人力资源管理",
      "politics": 41,
      "politics_str": "41",
      "english": 41,
      "english_str": "41",
      "special_one": 62,
      "special_one_str": "62",
      "special_two": 62,
      "special_two_str": "62",
      "total": 333,
      "note": "",
      "year": 2025,
      "degree_type": 2,
      "special_remark": "",
      "diff_total": 0,
      "diff_politics": 0,
      "diff_english": 0,
      "diff_special_one": 0,
      "diff_special_two": 0
    },
    {
      "id": 153021,
      "data_type": "score_level",
      "school_id": 951,
      "school_name": "重庆工商大学",
      "depart_id": 0,
      "depart_name": "不区分院系",
      "code": "1251",
      "name": "工商管理",
      "politics": 35,
      "politics_str": "35",
      "english": 35,
      "english_str": "35",
      "special_one": 70,
      "special_one_str": "70",
      "special_two": 70,
      "special_two_str": "70",
      "total": 151,
      "note": "",
      "year": 2025,
      "degree_type": 1,
      "special_remark": "",
      "diff_total": 0,
      "diff_politics": 0,
      "diff_english": 0,
      "diff_special_one": 0,
      "diff_special_two": 0
    },
    {
      "id": 153023,
      "data_type": "score_level",
      "school_id": 951,
      "school_name": "重庆工商大学",
      "depart_id": 0,
      "depart_name": "不区分院系",
      "code": "1252",
      "name": "公共管理",
      "politics": 38,
      "politics_str": "38",
      "english": 38,
      "english_str": "38",
      "special_one": 76,
      "special_one_str": "76",
      "special_two": 76,
      "special_two_str": "76",
      "total": 168,
      "note": "",
      "year": 2025,
      "degree_type": 1,
      "special_remark": "",
      "diff_total": 4,
      "diff_politics": 0,
      "diff_english": 0,
      "diff_special_one": 0,
      "diff_special_two": 0
    },
    {
      "id": 153024,
      "data_type": "score_level",
      "school_id": 951,
      "school_name": "重庆工商大学",
      "depart_id": 0,
      "depart_name": "不区分院系",
      "code": "1253",
      "name": "会计",
      "politics": 48,
      "politics_str": "48",
      "english": 48,
      "english_str": "48",
      "special_one": 96,
      "special_one_str": "96",
      "special_two": 96,
      "special_two_str": "96",
      "total": 209,
      "note": "",
      "year": 2025,
      "degree_type": 1,
      "special_remark": "",
      "diff_total": 15,
      "diff_politics": 0,
      "diff_english": 0,
      "diff_special_one": 0,
      "diff_special_two": 0
    },
    {
      "id": 153022,
      "data_type": "score_level",
      "school_id": 951,
      "school_name": "重庆工商大学",
      "depart_id": 0,
      "depart_name": "不区分院系",
      "code": "1254",
      "name": "旅游管理",
      "politics": 35,
      "politics_str": "35",
      "english": 35,
      "english_str": "35",
      "special_one": 70,
      "special_one_str": "70",
      "special_two": 70,
      "special_two_str": "70",
      "total": 151,
      "note": "",
      "year": 2025,
      "degree_type": 1,
      "special_remark": "",
      "diff_total": 0,
      "diff_politics": 0,
      "diff_english": 0,
      "diff_special_one": 0,
      "diff_special_two": 0
    },
    {
      "id": 153026,
      "data_type": "score_level",
      "school_id": 951,
      "school_name": "重庆工商大学",
      "depart_id": 0,
      "depart_name": "不区分院系",
      "code": "1256",
      "name": "工程管理",
      "politics": 38,
      "politics_str": "38",
      "english": 38,
      "english_str": "38",
      "special_one": 76,
      "special_one_str": "76",
      "special_two": 76,
      "special_two_str": "76",
      "total": 162,
      "note": "",
      "year": 2025,
      "degree_type": 1,
      "special_remark": "",
      "diff_total": 0,
      "diff_politics": 0,
      "diff_english": 0,
      "diff_special_one": 0,
      "diff_special_two": 0
    },
    {
      "id": 153025,
      "data_type": "score_level",
      "school_id": 951,
      "school_name": "重庆工商大学",
      "depart_id": 0,
      "depart_name": "不区分院系",
      "code": "1257",
      "name": "审计",
      "politics": 48,
      "politics_str": "48",
      "english": 48,
      "english_str": "48",
      "special_one": 96,
      "special_one_str": "96",
      "special_two": 96,
      "special_two_str": "96",
      "total": 198,
      "note": "",
      "year": 2025,
      "degree_type": 1,
      "special_remark": "",
      "diff_total": 4,
      "diff_politics": 0,
      "diff_english": 0,
      "diff_special_one": 0,
      "diff_special_two": 0
    },
    {
      "id": 153027,
      "data_type": "score_level",
      "school_id": 951,
      "school_name": "重庆工商大学",
      "depart_id": 0,
      "depart_name": "不区分院系",
      "code": "1357",
      "name": "设计",
      "politics": 37,
      "politics_str": "37",
      "english": 37,
      "english_str": "37",
      "special_one": 56,
      "special_one_str": "56",
      "special_two": 56,
      "special_two_str": "56",
      "total": 351,
      "note": "",
      "year": 2025,
      "degree_type": 1,
      "special_remark": "",
      "diff_total": 0,
      "diff_politics": 0,
      "diff_english": 0,
      "diff_special_one": 0,
      "diff_special_two": 0
    }
  ],
  "message": "success"
}