{
  "code": "0000",
  "data": [
    {
      "id": "543055_237",
      "data_type": "school_score",
      "school_id": 1016,
      "school_name": "陆军勤务学院",
      "depart_id": 0,
      "depart_name": "不区分院系",
      "code": "020200",
      "name": "应用经济学",
      "politics": 52,
      "politics_str": "52",
      "english": 52,
      "english_str": "52",
      "special_one": 78,
      "special_one_str": "78",
      "special_two": 78,
      "special_two_str": "78",
      "total": 360,
      "note": "",
      "year": 2022,
      "degree_type": 2,
      "special_remark": "",
      "diff_total": 0,
      "diff_politics": 0,
      "diff_english": 0,
      "diff_special_one": 0,
      "diff_special_two": 0
    },
    {
      "id": "555733_7",
      "data_type": "school_score",
      "school_id": 1016,
      "school_name": "陆军勤务学院",
      "depart_id": 0,
      "depart_name": "不区分院系",
      "code": "025700",
      "name": "审计",
      "politics": 0,
      "politics_str": "--",
      "english": 50,
      "english_str": "50",
      "special_one": 100,
      "special_one_str": "100",
      "special_two": 0,
      "special_two_str": "--",
      "total": 194,
      "note": "",
      "year": 2022,
      "degree_type": 1,
      "special_remark": "",
      "diff_total": 0,
      "diff_politics": 0,
      "diff_english": 0,
      "diff_special_one": 0,
      "diff_special_two": 0
    },
    {
      "id": "543056_502",
      "data_type": "school_score",
      "school_id": 1016,
      "school_name": "陆军勤务学院",
      "depart_id": 0,
      "depart_name": "不区分院系",
      "code": "081300",
      "name": "建筑学",
      "politics": 38,
      "politics_str": "38",
      "english": 38,
      "english_str": "38",
      "special_one": 57,
      "special_one_str": "57",
      "special_two": 57,
      "special_two_str": "57",
      "total": 273,
      "note": "",
      "year": 2022,
      "degree_type": 2,
      "special_remark": "",
      "diff_total": 0,
      "diff_politics": 0,
      "diff_english": 0,
      "diff_special_one": 0,
      "diff_special_two": 0
    },
    {
      "id": "543057_506",
      "data_type": "school_score",
      "school_id": 1016,
      "school_name": "陆军勤务学院",
      "depart_id": 0,
      "depart_name": "不区分院系",
      "code": "081400",
      "name": "土木工程",
      "politics": 38,
      "politics_str": "38",
      "english": 38,
      "english_str": "38",
      "special_one": 57,
      "special_one_str": "57",
      "special_two": 57,
      "special_two_str": "57",
      "total": 273,
      "note": "",
      "year": 2022,
      "degree_type": 2,
      "special_remark": "",
      "diff_total": 0,
      "diff_politics": 0,
      "diff_english": 0,
      "diff_special_one": 0,
      "diff_special_two": 0
    },
    {
      "id": "543058_537",
      "data_type": "school_score",
      "school_id": 1016,
      "school_name": "陆军勤务学院",
      "depart_id": 0,
      "depart_name": "不区分院系",
      "code": "082000",
      "name": "石油与天然气工程",
      "politics": 38,
      "politics_str": "38",
      "english": 38,
      "english_str": "38",
      "special_one": 57,
      "special_one_str": "57",
      "special_two": 57,
      "special_two_str": "57",
      "total": 273,
      "note": "",
      "year": 2022,
      "degree_type": 2,
      "special_remark": "",
      "diff_total": 0,
      "diff_politics": 0,
      "diff_english": 0,
      "diff_special_one": 0,
      "diff_special_two": 0
    },
    {
      "id": "543059_584",
      "data_type": "school_score",
      "school_id": 1016,
      "school_name": "陆军勤务学院",
      "depart_id": 0,
      "depart_name": "不区分院系",
      "code": "083000",
      "name": "环境科学与工程",
      "politics": 38,
      "politics_str": "38",
      "english": 38,
      "english_str": "38",
      "special_one": 57,
      "special_one_str": "57",
      "special_two": 57,
      "special_two_str": "57",
      "total": 273,
      "note": "",
      "year": 2022,
      "degree_type": 2,
      "special_remark": "",
      "diff_total": 0,
      "diff_politics": 0,
      "diff_english": 0,
      "diff_special_one": 0,
      "diff_special_two": 0
    },
    {
      "id": "543064_77",
      "data_type": "school_score",
      "school_id": 1016,
      "school_name": "陆军勤务学院",
      "depart_id": 0,
      "depart_name": "不区分院系",
      "code": "085400",
      "name": "电子信息",
      "politics": 38,
      "politics_str": "38",
      "english": 38,
      "english_str": "38",
      "special_one": 57,
      "special_one_str": "57",
      "special_two": 57,
      "special_two_str": "57",
      "total": 273,
      "note": "",
      "year": 2022,
      "degree_type": 1,
      "special_remark": "",
      "diff_total": 0,
      "diff_politics": 0,
      "diff_english": 0,
      "diff_special_one": 0,
      "diff_special_two": 0
    },
    {
      "id": "543065_101",
      "data_type": "school_score",
      "school_id": 1016,
      "school_name": "陆军勤务学院",
      "depart_id": 0,
      "depart_name": "不区分院系",
      "code": "085600",
      "name": "材料与化工",
      "politics": 38,
      "politics_str": "38",
      "english": 38,
      "english_str": "38",
      "special_one": 57,
      "special_one_str": "57",
      "special_two": 57,
      "special_two_str": "57",
      "total": 273,
      "note": "",
      "year": 2022,
      "degree_type": 1,
      "special_remark": "",
      "diff_total": 0,
      "diff_politics": 0,
      "diff_english": 0,
      "diff_special_one": 0,
      "diff_special_two": 0
    },
    {
      "id": "543066_108",
      "data_type": "school_score",
      "school_id": 1016,
      "school_name": "陆军勤务学院",
      "depart_id": 0,
      "depart_name": "不区分院系",
      "code": "085700",
      "name": "资源与环境",
      "politics": 38,
      "politics_str": "38",
      "english": 38,
      "english_str": "38",
      "special_one": 57,
      "special_one_str": "57",
      "special_two": 57,
      "special_two_str": "57",
      "total": 273,
      "note": "",
      "year": 2022,
      "degree_type": 1,
      "special_remark": "",
      "diff_total": 0,
      "diff_politics": 0,
      "diff_english": 0,
      "diff_special_one": 0,
      "diff_special_two": 0
    },
    {
      "id": "543067_115",
      "data_type": "school_score",
      "school_id": 1016,
      "school_name": "陆军勤务学院",
      "depart_id": 0,
      "depart_name": "不区分院系",
      "code": "085800",
      "name": "能源动力",
      "politics": 38,
      "politics_str": "38",
      "english": 38,
      "english_str": "38",
      "special_one": 57,
      "special_one_str": "57",
      "special_two": 57,
      "special_two_str": "57",
      "total": 273,
      "note": "",
      "year": 2022,
      "degree_type": 1,
      "special_remark": "",
      "diff_total": 0,
      "diff_politics": 0,
      "diff_english": 0,
      "diff_special_one": 0,
      "diff_special_two": 0
    },
    {
      "id": "543068_124",
      "data_type": "school_score",
      "school_id": 1016,
      "school_name": "陆军勤务学院",
      "depart_id": 0,
      "depart_name": "不区分院系",
      "code": "085900",
      "name": "土木水利",
      "politics": 38,
      "politics_str": "38",
      "english": 38,
      "english_str": "38",
      "special_one": 57,
      "special_one_str": "57",
      "special_two": 57,
      "special_two_str": "57",
      "total": 273,
      "note": "",
      "year": 2022,
      "degree_type": 1,
      "special_remark": "",
      "diff_total": 0,
      "diff_politics": 0,
      "diff_english": 0,
      "diff_special_one": 0,
      "diff_special_two": 0
    },
    {
      "id": "543060_745",
      "data_type": "school_score",
      "school_id": 1016,
      "school_name": "陆军勤务学院",
      "depart_id": 0,
      "depart_name": "不区分院系",
      "code": "110800",
      "name": "军事后勤学",
      "politics": 37,
      "politics_str": "37",
      "english": 37,
      "english_str": "37",
      "special_one": 56,
      "special_one_str": "56",
      "special_two": 56,
      "special_two_str": "56",
      "total": 265,
      "note": "",
      "year": 2022,
      "degree_type": 2,
      "special_remark": "",
      "diff_total": 0,
      "diff_politics": 0,
      "diff_english": 0,
      "diff_special_one": 0,
      "diff_special_two": 0
    },
    {
      "id": "543061_749",
      "data_type": "school_score",
      "school_id": 1016,
      "school_name": "陆军勤务学院",
      "depart_id": 0,
      "depart_name": "不区分院系",
      "code": "110900",
      "name": "军事装备学",
      "politics": 37,
      "politics_str": "37",
      "english": 37,
      "english_str": "37",
      "special_one": 56,
      "special_one_str": "56",
      "special_two": 56,
      "special_two_str": "56",
      "total": 265,
      "note": "",
      "year": 2022,
      "degree_type": 2,
      "special_remark": "",
      "diff_total": 0,
      "diff_politics": 0,
      "diff_english": 0,
      "diff_special_one": 0,
      "diff_special_two": 0
    },
    {
      "id": "543069_200",
      "data_type": "school_score",
      "school_id": 1016,
      "school_name": "陆军勤务学院",
      "depart_id": 0,
      "depart_name": "不区分院系",
      "code": "115103",
      "name": "军事后勤",
      "politics": 37,
      "politics_str": "37",
      "english": 37,
      "english_str": "37",
      "special_one": 56,
      "special_one_str": "56",
      "special_two": 56,
      "special_two_str": "56",
      "total": 265,
      "note": "",
      "year": 2022,
      "degree_type": 1,
      "special_remark": "",
      "diff_total": 0,
      "diff_politics": 0,
      "diff_english": 0,
      "diff_special_one": 0,
      "diff_special_two": 0
    },
    {
      "id": "543070_201",
      "data_type": "school_score",
      "school_id": 1016,
      "school_name": "陆军勤务学院",
      "depart_id": 0,
      "depart_name": "不区分院系",
      "code": "115104",
      "name": "军事装备",
      "politics": 37,
      "politics_str": "37",
      "english": 37,
      "english_str": "37",
      "special_one": 56,
      "special_one_str": "56",
      "special_two": 56,
      "special_two_str": "56",
      "total": 265,
      "note": "",
      "year": 2022,
      "degree_type": 1,
      "special_remark": "",
      "diff_total": 0,
      "diff_politics": 0,
      "diff_english": 0,
      "diff_special_one": 0,
      "diff_special_two": 0
    },
    {
      "id": "543062_759",
      "data_type": "school_score",
      "school_id": 1016,
      "school_name": "陆军勤务学院",
      "depart_id": 0,
      "depart_name": "不区分院系",
      "code": "120100",
      "name": "管理科学与工程",
      "politics": 51,
      "politics_str": "51",
      "english": 51,
      "english_str": "51",
      "special_one": 77,
      "special_one_str": "77",
      "special_two": 77,
      "special_two_str": "77",
      "total": 353,
      "note": "",
      "year": 2022,
      "degree_type": 2,
      "special_remark": "",
      "diff_total": 0,
      "diff_politics": 0,
      "diff_english": 0,
      "diff_special_one": 0,
      "diff_special_two": 0
    },
    {
      "id": "555734_204",
      "data_type": "school_score",
      "school_id": 1016,
      "school_name": "陆军勤务学院",
      "depart_id": 0,
      "depart_name": "不区分院系",
      "code": "125300",
      "name": "会计",
      "politics": 0,
      "politics_str": "--",
      "english": 50,
      "english_str": "50",
      "special_one": 100,
      "special_one_str": "100",
      "special_two": 0,
      "special_two_str": "--",
      "total": 193,
      "note": "",
      "year": 2022,
      "degree_type": 1,
      "special_remark": "",
      "diff_total": 0,
      "diff_politics": 0,
      "diff_english": 0,
      "diff_special_one": 0,
      "diff_special_two": 0
    },
    {
      "id": "555735_207",
      "data_type": "school_score",
      "school_id": 1016,
      "school_name": "陆军勤务学院",
      "depart_id": 0,
      "depart_name": "不区分院系",
      "code": "125600",
      "name": "工程管理",
      "politics": 0,
      "politics_str": "--",
      "english": 47,
      "english_str": "47",
      "special_one": 94,
      "special_one_str": "94",
      "special_two": 0,
      "special_two_str": "--",
      "total": 189,
      "note": "",
      "year": 2022,
      "degree_type": 1,
      "special_remark": "",
      "diff_total": 0,
      "diff_politics": 0,
      "diff_english": 0,
      "diff_special_one": 0,
      "diff_special_two": 0
    }
  ],
  "message": "success"
}