{
  "code": "0000",
  "data": {
    "total": 3,
    "data": [
      {
        "spe_id": 91,
        "year": 2023,
        "depart_id": 0,
        "special_code": "085501",
        "special_name": "机械工程",
        "recruit_type_name": "全日制",
        "depart_name": "不区分院系",
        "exam_class": 1,
        "degree_type": 1,
        "research_area": "01 先进制\n造系统与\n工程；02 机器人\n技术与应\n用；03 智能测\n试系统与\n传感器",
        "exam_subject": "①101 思想政治\n理论<br/>②204 英语二<br/>③302 数学二<br/>④806 机械设计 基础<br/>",
        "recruit_number": 40,
        "degree_type_name": "专业型硕士",
        "plan_id": 945275,
        "exam_class_name": "统考",
        "remark": ""
      },
      {
        "spe_id": 102,
        "year": 2023,
        "depart_id": 0,
        "special_code": "085601",
        "special_name": "材料工程",
        "recruit_type_name": "全日制",
        "depart_name": "不区分院系",
        "exam_class": 1,
        "degree_type": 1,
        "research_area": "01 表面工程材料02 光电功能材料；03 生物医药材料；04 环境功能材料",
        "exam_subject": "①101 思想政治\n理论<br/>②204 英语二<br/>③302 数学二<br/>④801 材料科学\n基础<br/>",
        "recruit_number": 40,
        "degree_type_name": "专业型硕士",
        "plan_id": 945273,
        "exam_class_name": "统考",
        "remark": ""
      },
      {
        "spe_id": 143,
        "year": 2023,
        "depart_id": 0,
        "special_code": "095131",
        "special_name": "农艺与种业",
        "recruit_type_name": "全日制",
        "depart_name": "不区分院系",
        "exam_class": 1,
        "degree_type": 1,
        "research_area": "01 园艺种\n质资源保\n护与利用；02 种苗研\n发与工厂\n化生产；03 山地植\n物生产与\n调控",
        "exam_subject": "①101 思想政治\n理论<br/>②204 英语二<br/>③339 农业知识 综合一<br/>④853 园艺植物 栽培与育种学<br/>",
        "recruit_number": 40,
        "degree_type_name": "专业型硕士",
        "plan_id": 945274,
        "exam_class_name": "统考",
        "remark": ""
      }
    ]
  },
  "message": "success"
}