{
  "code": "0000",
  "data": {
    "total": 415,
    "data": [
      {
        "spe_id": 20134,
        "year": 2025,
        "depart_id": 15739,
        "special_code": "045300",
        "special_name": "国际中文教育",
        "recruit_type_name": "全日制",
        "depart_name": "外国语学院",
        "exam_class": 1,
        "degree_type": 1,
        "research_area": "（00）入校后确定研究方向",
        "exam_subject": "①(101)思想政治理论<br/>②(201)英语（一）<br/>③(354)汉语基础<br/>④(445)汉语国际教育基础<br/>",
        "recruit_number": 10,
        "degree_type_name": "专业型硕士",
        "is_statistic_direction": 1,
        "plan_id": 1236620,
        "exam_class_name": "统考",
        "remark": "招生人数为专业招生总数，非方向人数"
      },
      {
        "spe_id": 20146,
        "year": 2025,
        "depart_id": 15739,
        "special_code": "050200",
        "special_name": "外国语言文学",
        "recruit_type_name": "全日制",
        "depart_name": "外国语学院",
        "exam_class": 1,
        "degree_type": 2,
        "research_area": "（02）外国文学",
        "exam_subject": "①(101)思想政治理论<br/>②(243)日语（二外）限英语专业报考 或 (244)德语（二外） 或 (245)法语（二外）<br/>③(615)基础英语<br/>④(814)英语语言文学综合<br/>",
        "recruit_number": 11,
        "degree_type_name": "学术型硕士",
        "is_statistic_direction": 1,
        "plan_id": 1206689,
        "exam_class_name": "统考",
        "remark": "招生人数为专业招生总数，非方向人数"
      },
      {
        "spe_id": 20146,
        "year": 2025,
        "depart_id": 15739,
        "special_code": "050200",
        "special_name": "外国语言文学",
        "recruit_type_name": "全日制",
        "depart_name": "外国语学院",
        "exam_class": 1,
        "degree_type": 2,
        "research_area": "（01）外国语言学及应用语言学",
        "exam_subject": "①(101)思想政治理论<br/>②(243)日语（二外）限英语专业报考 或 (244)德语（二外） 或 (245)法语（二外）<br/>③(615)基础英语<br/>④(814)英语语言文学综合<br/>",
        "recruit_number": 11,
        "degree_type_name": "学术型硕士",
        "is_statistic_direction": 1,
        "plan_id": 1246835,
        "exam_class_name": "统考",
        "remark": "招生人数为专业招生总数，非方向人数"
      },
      {
        "spe_id": 20161,
        "year": 2025,
        "depart_id": 15739,
        "special_code": "055100",
        "special_name": "翻译",
        "recruit_type_name": "全日制",
        "depart_name": "外国语学院",
        "exam_class": 1,
        "degree_type": 1,
        "research_area": "（01）英语笔译",
        "exam_subject": "①(101)思想政治理论<br/>②(211)翻译硕士（英语）<br/>③(357)翻译基础（英语）<br/>④(448)汉语写作与百科知识<br/>",
        "recruit_number": 18,
        "degree_type_name": "专业型硕士",
        "is_statistic_direction": 1,
        "plan_id": 1148065,
        "exam_class_name": "统考",
        "remark": "招生人数为专业招生总数，非方向人数"
      },
      {
        "spe_id": 20761,
        "year": 2025,
        "depart_id": 15740,
        "special_code": "130100",
        "special_name": "艺术学",
        "recruit_type_name": "全日制",
        "depart_name": "艺术学院",
        "exam_class": 1,
        "degree_type": 2,
        "research_area": "（02）中国近现代艺术史论研究",
        "exam_subject": "①(101)思想政治理论<br/>②(201)英语（一）<br/>③(617)艺术理论<br/>④(816)艺术史与作品分析<br/>",
        "recruit_number": 5,
        "degree_type_name": "学术型硕士",
        "is_statistic_direction": 1,
        "plan_id": 1155848,
        "exam_class_name": "统考",
        "remark": "招生人数为专业招生总数，非方向人数"
      },
      {
        "spe_id": 20761,
        "year": 2025,
        "depart_id": 15740,
        "special_code": "130100",
        "special_name": "艺术学",
        "recruit_type_name": "全日制",
        "depart_name": "艺术学院",
        "exam_class": 1,
        "degree_type": 2,
        "research_area": "（03）西南民族民间艺术研究",
        "exam_subject": "①(101)思想政治理论<br/>②(201)英语（一）<br/>③(617)艺术理论<br/>④(816)艺术史与作品分析<br/>",
        "recruit_number": 5,
        "degree_type_name": "学术型硕士",
        "is_statistic_direction": 1,
        "plan_id": 1200306,
        "exam_class_name": "统考",
        "remark": "招生人数为专业招生总数，非方向人数"
      },
      {
        "spe_id": 20761,
        "year": 2025,
        "depart_id": 15740,
        "special_code": "130100",
        "special_name": "艺术学",
        "recruit_type_name": "全日制",
        "depart_name": "艺术学院",
        "exam_class": 1,
        "degree_type": 2,
        "research_area": "（01）艺术历史与理论",
        "exam_subject": "①(101)思想政治理论<br/>②(201)英语（一）<br/>③(617)艺术理论<br/>④(816)艺术史与作品分析<br/>",
        "recruit_number": 5,
        "degree_type_name": "学术型硕士",
        "is_statistic_direction": 1,
        "plan_id": 1208339,
        "exam_class_name": "统考",
        "remark": "招生人数为专业招生总数，非方向人数"
      },
      {
        "spe_id": 20770,
        "year": 2025,
        "depart_id": 15740,
        "special_code": "135600",
        "special_name": "美术与书法",
        "recruit_type_name": "全日制",
        "depart_name": "艺术学院",
        "exam_class": 1,
        "degree_type": 1,
        "research_area": "（03）油画",
        "exam_subject": "①(101)思想政治理论<br/>②(204)英语（二）<br/>③(617)艺术理论<br/>④(816)艺术史与作品分析<br/>",
        "recruit_number": 5,
        "degree_type_name": "专业型硕士",
        "is_statistic_direction": 1,
        "plan_id": 1164653,
        "exam_class_name": "统考",
        "remark": "招生人数为专业招生总数，非方向人数"
      },
      {
        "spe_id": 20770,
        "year": 2025,
        "depart_id": 15740,
        "special_code": "135600",
        "special_name": "美术与书法",
        "recruit_type_name": "全日制",
        "depart_name": "艺术学院",
        "exam_class": 1,
        "degree_type": 1,
        "research_area": "（02）书法",
        "exam_subject": "①(101)思想政治理论<br/>②(204)英语（二）<br/>③(617)艺术理论<br/>④(816)艺术史与作品分析<br/>",
        "recruit_number": 5,
        "degree_type_name": "专业型硕士",
        "is_statistic_direction": 1,
        "plan_id": 1186491,
        "exam_class_name": "统考",
        "remark": "招生人数为专业招生总数，非方向人数"
      },
      {
        "spe_id": 20770,
        "year": 2025,
        "depart_id": 15740,
        "special_code": "135600",
        "special_name": "美术与书法",
        "recruit_type_name": "全日制",
        "depart_name": "艺术学院",
        "exam_class": 1,
        "degree_type": 1,
        "research_area": "（01）中国画",
        "exam_subject": "①(101)思想政治理论<br/>②(204)英语（二）<br/>③(617)艺术理论<br/>④(816)艺术史与作品分析<br/>",
        "recruit_number": 5,
        "degree_type_name": "专业型硕士",
        "is_statistic_direction": 1,
        "plan_id": 1203401,
        "exam_class_name": "统考",
        "remark": "招生人数为专业招生总数，非方向人数"
      },
      {
        "spe_id": 20771,
        "year": 2025,
        "depart_id": 15740,
        "special_code": "135700",
        "special_name": "设计",
        "recruit_type_name": "全日制",
        "depart_name": "艺术学院",
        "exam_class": 1,
        "degree_type": 1,
        "research_area": "（04）数字创意设计",
        "exam_subject": "①(101)思想政治理论<br/>②(204)英语（二）<br/>③(617)艺术理论<br/>④(816)艺术史与作品分析<br/>",
        "recruit_number": 12,
        "degree_type_name": "专业型硕士",
        "is_statistic_direction": 1,
        "plan_id": 1142355,
        "exam_class_name": "统考",
        "remark": "招生人数为专业招生总数，非方向人数"
      },
      {
        "spe_id": 20771,
        "year": 2025,
        "depart_id": 15740,
        "special_code": "135700",
        "special_name": "设计",
        "recruit_type_name": "全日制",
        "depart_name": "艺术学院",
        "exam_class": 1,
        "degree_type": 1,
        "research_area": "（01）工业设计",
        "exam_subject": "①(101)思想政治理论<br/>②(204)英语（二）<br/>③(617)艺术理论<br/>④(816)艺术史与作品分析<br/>",
        "recruit_number": 12,
        "degree_type_name": "专业型硕士",
        "is_statistic_direction": 1,
        "plan_id": 1149278,
        "exam_class_name": "统考",
        "remark": "招生人数为专业招生总数，非方向人数"
      },
      {
        "spe_id": 20771,
        "year": 2025,
        "depart_id": 15740,
        "special_code": "135700",
        "special_name": "设计",
        "recruit_type_name": "全日制",
        "depart_name": "艺术学院",
        "exam_class": 1,
        "degree_type": 1,
        "research_area": "（03）环境艺术设计",
        "exam_subject": "①(101)思想政治理论<br/>②(204)英语（二）<br/>③(617)艺术理论<br/>④(816)艺术史与作品分析<br/>",
        "recruit_number": 12,
        "degree_type_name": "专业型硕士",
        "is_statistic_direction": 1,
        "plan_id": 1162185,
        "exam_class_name": "统考",
        "remark": "招生人数为专业招生总数，非方向人数"
      },
      {
        "spe_id": 20771,
        "year": 2025,
        "depart_id": 15740,
        "special_code": "135700",
        "special_name": "设计",
        "recruit_type_name": "全日制",
        "depart_name": "艺术学院",
        "exam_class": 1,
        "degree_type": 1,
        "research_area": "（02）视觉传达设计",
        "exam_subject": "①(101)思想政治理论<br/>②(204)英语（二）<br/>③(617)艺术理论<br/>④(816)艺术史与作品分析<br/>",
        "recruit_number": 12,
        "degree_type_name": "专业型硕士",
        "is_statistic_direction": 1,
        "plan_id": 1191825,
        "exam_class_name": "统考",
        "remark": "招生人数为专业招生总数，非方向人数"
      },
      {
        "spe_id": 20772,
        "year": 2025,
        "depart_id": 15740,
        "special_code": "137000",
        "special_name": "设计学",
        "recruit_type_name": "全日制",
        "depart_name": "艺术学院",
        "exam_class": 1,
        "degree_type": 2,
        "research_area": "（02）数智人居与城乡文化遗产保护再利用",
        "exam_subject": "①(101)思想政治理论<br/>②(201)英语（一）<br/>③(617)艺术理论<br/>④(816)艺术史与作品分析<br/>",
        "recruit_number": 5,
        "degree_type_name": "学术型硕士",
        "is_statistic_direction": 1,
        "plan_id": 1152661,
        "exam_class_name": "统考",
        "remark": "招生人数为专业招生总数，非方向人数"
      },
      {
        "spe_id": 20772,
        "year": 2025,
        "depart_id": 15740,
        "special_code": "137000",
        "special_name": "设计学",
        "recruit_type_name": "全日制",
        "depart_name": "艺术学院",
        "exam_class": 1,
        "degree_type": 2,
        "research_area": "（03）数智产品创新与视觉传播设计",
        "exam_subject": "①(101)思想政治理论<br/>②(201)英语（一）<br/>③(617)艺术理论<br/>④(816)艺术史与作品分析<br/>",
        "recruit_number": 5,
        "degree_type_name": "学术型硕士",
        "is_statistic_direction": 1,
        "plan_id": 1226102,
        "exam_class_name": "统考",
        "remark": "招生人数为专业招生总数，非方向人数"
      },
      {
        "spe_id": 20772,
        "year": 2025,
        "depart_id": 15740,
        "special_code": "137000",
        "special_name": "设计学",
        "recruit_type_name": "全日制",
        "depart_name": "艺术学院",
        "exam_class": 1,
        "degree_type": 2,
        "research_area": "（01）设计历史与理论",
        "exam_subject": "①(101)思想政治理论<br/>②(201)英语（一）<br/>③(617)艺术理论<br/>④(816)艺术史与作品分析<br/>",
        "recruit_number": 5,
        "degree_type_name": "学术型硕士",
        "is_statistic_direction": 1,
        "plan_id": 1230652,
        "exam_class_name": "统考",
        "remark": "招生人数为专业招生总数，非方向人数"
      },
      {
        "spe_id": 20129,
        "year": 2025,
        "depart_id": 15741,
        "special_code": "045200",
        "special_name": "体育",
        "recruit_type_name": "全日制",
        "depart_name": "体育学院",
        "exam_class": 1,
        "degree_type": 1,
        "research_area": "（02）运动训练",
        "exam_subject": "①(101)思想政治理论<br/>②(204)英语（二）<br/>③(346)体育综合<br/>④(--)无<br/>",
        "recruit_number": 5,
        "degree_type_name": "专业型硕士",
        "is_statistic_direction": 1,
        "plan_id": 1243529,
        "exam_class_name": "统考",
        "remark": "招生人数为专业招生总数，非方向人数"
      },
      {
        "spe_id": 20129,
        "year": 2025,
        "depart_id": 15741,
        "special_code": "045200",
        "special_name": "体育",
        "recruit_type_name": "全日制",
        "depart_name": "体育学院",
        "exam_class": 1,
        "degree_type": 1,
        "research_area": "（01）体育教学",
        "exam_subject": "①(101)思想政治理论<br/>②(204)英语（二）<br/>③(346)体育综合<br/>④(--)无<br/>",
        "recruit_number": 5,
        "degree_type_name": "专业型硕士",
        "is_statistic_direction": 1,
        "plan_id": 1253540,
        "exam_class_name": "统考",
        "remark": "招生人数为专业招生总数，非方向人数"
      },
      {
        "spe_id": 20761,
        "year": 2025,
        "depart_id": 15742,
        "special_code": "130100",
        "special_name": "艺术学",
        "recruit_type_name": "全日制",
        "depart_name": "美视电影学院",
        "exam_class": 1,
        "degree_type": 2,
        "research_area": "（00）入校后确定研究方向",
        "exam_subject": "①(101)思想政治理论<br/>②(201)英语（一）<br/>③(673)影视艺术理论<br/>④(867)中外电影史<br/>",
        "recruit_number": 10,
        "degree_type_name": "学术型硕士",
        "is_statistic_direction": 1,
        "plan_id": 1204046,
        "exam_class_name": "统考",
        "remark": "招生人数为专业招生总数，非方向人数"
      },
      {
        "spe_id": 20768,
        "year": 2025,
        "depart_id": 15742,
        "special_code": "135400",
        "special_name": "戏剧与影视",
        "recruit_type_name": "全日制",
        "depart_name": "美视电影学院",
        "exam_class": 1,
        "degree_type": 1,
        "research_area": "（00）入校后确定研究方向",
        "exam_subject": "①(101)思想政治理论<br/>②(204)英语（二）<br/>③(673)影视艺术理论<br/>④(933)影视艺术创作<br/>",
        "recruit_number": 9,
        "degree_type_name": "专业型硕士",
        "is_statistic_direction": 1,
        "plan_id": 1186283,
        "exam_class_name": "统考",
        "remark": "招生人数为专业招生总数，非方向人数"
      },
      {
        "spe_id": 20001,
        "year": 2025,
        "depart_id": 15746,
        "special_code": "010100",
        "special_name": "哲学",
        "recruit_type_name": "全日制",
        "depart_name": "人文社会科学高等研究院",
        "exam_class": 1,
        "degree_type": 2,
        "research_area": "（03）古典学",
        "exam_subject": "①(101)思想政治理论<br/>②(201)英语（一）<br/>③(656)中国哲学史<br/>④(882)西方哲学史<br/>",
        "recruit_number": 1,
        "degree_type_name": "学术型硕士",
        "is_statistic_direction": 1,
        "plan_id": 1142437,
        "exam_class_name": "统考",
        "remark": "招生人数为专业招生总数，非方向人数"
      },
      {
        "spe_id": 20001,
        "year": 2025,
        "depart_id": 15746,
        "special_code": "010100",
        "special_name": "哲学",
        "recruit_type_name": "全日制",
        "depart_name": "人文社会科学高等研究院",
        "exam_class": 1,
        "degree_type": 2,
        "research_area": "（02）外国哲学",
        "exam_subject": "①(101)思想政治理论<br/>②(201)英语（一）<br/>③(656)中国哲学史<br/>④(882)西方哲学史<br/>",
        "recruit_number": 1,
        "degree_type_name": "学术型硕士",
        "is_statistic_direction": 1,
        "plan_id": 1181612,
        "exam_class_name": "统考",
        "remark": "招生人数为专业招生总数，非方向人数"
      },
      {
        "spe_id": 20001,
        "year": 2025,
        "depart_id": 15746,
        "special_code": "010100",
        "special_name": "哲学",
        "recruit_type_name": "全日制",
        "depart_name": "人文社会科学高等研究院",
        "exam_class": 1,
        "degree_type": 2,
        "research_area": "（01）中国哲学",
        "exam_subject": "①(101)思想政治理论<br/>②(201)英语（一）<br/>③(656)中国哲学史<br/>④(882)西方哲学史<br/>",
        "recruit_number": 1,
        "degree_type_name": "学术型硕士",
        "is_statistic_direction": 1,
        "plan_id": 1243764,
        "exam_class_name": "统考",
        "remark": "招生人数为专业招生总数，非方向人数"
      },
      {
        "spe_id": 20137,
        "year": 2025,
        "depart_id": 15746,
        "special_code": "050100",
        "special_name": "中国语言文学",
        "recruit_type_name": "全日制",
        "depart_name": "人文社会科学高等研究院",
        "exam_class": 1,
        "degree_type": 2,
        "research_area": "（03）中国现当代文学",
        "exam_subject": "①(101)思想政治理论<br/>②(201)英语（一）<br/>③(633)语言文学综合<br/>④(880)写作<br/>",
        "recruit_number": 2,
        "degree_type_name": "学术型硕士",
        "is_statistic_direction": 1,
        "plan_id": 1156293,
        "exam_class_name": "统考",
        "remark": "招生人数为专业招生总数，非方向人数"
      },
      {
        "spe_id": 20137,
        "year": 2025,
        "depart_id": 15746,
        "special_code": "050100",
        "special_name": "中国语言文学",
        "recruit_type_name": "全日制",
        "depart_name": "人文社会科学高等研究院",
        "exam_class": 1,
        "degree_type": 2,
        "research_area": "（01）比较文学与世界文学",
        "exam_subject": "①(101)思想政治理论<br/>②(201)英语（一）<br/>③(633)语言文学综合<br/>④(880)写作<br/>",
        "recruit_number": 2,
        "degree_type_name": "学术型硕士",
        "is_statistic_direction": 1,
        "plan_id": 1158167,
        "exam_class_name": "统考",
        "remark": "招生人数为专业招生总数，非方向人数"
      },
      {
        "spe_id": 20137,
        "year": 2025,
        "depart_id": 15746,
        "special_code": "050100",
        "special_name": "中国语言文学",
        "recruit_type_name": "全日制",
        "depart_name": "人文社会科学高等研究院",
        "exam_class": 1,
        "degree_type": 2,
        "research_area": "（04）民间文学",
        "exam_subject": "①(101)思想政治理论<br/>②(201)英语（一）<br/>③(633)语言文学综合<br/>④(880)写作<br/>",
        "recruit_number": 2,
        "degree_type_name": "学术型硕士",
        "is_statistic_direction": 1,
        "plan_id": 1180546,
        "exam_class_name": "统考",
        "remark": "招生人数为专业招生总数，非方向人数"
      },
      {
        "spe_id": 20137,
        "year": 2025,
        "depart_id": 15746,
        "special_code": "050100",
        "special_name": "中国语言文学",
        "recruit_type_name": "全日制",
        "depart_name": "人文社会科学高等研究院",
        "exam_class": 1,
        "degree_type": 2,
        "research_area": "（06）中国古典文献学",
        "exam_subject": "①(101)思想政治理论<br/>②(201)英语（一）<br/>③(633)语言文学综合<br/>④(880)写作<br/>",
        "recruit_number": 2,
        "degree_type_name": "学术型硕士",
        "is_statistic_direction": 1,
        "plan_id": 1188757,
        "exam_class_name": "统考",
        "remark": "招生人数为专业招生总数，非方向人数"
      },
      {
        "spe_id": 20137,
        "year": 2025,
        "depart_id": 15746,
        "special_code": "050100",
        "special_name": "中国语言文学",
        "recruit_type_name": "全日制",
        "depart_name": "人文社会科学高等研究院",
        "exam_class": 1,
        "degree_type": 2,
        "research_area": "（07）中国古代文学",
        "exam_subject": "①(101)思想政治理论<br/>②(201)英语（一）<br/>③(633)语言文学综合<br/>④(880)写作<br/>",
        "recruit_number": 2,
        "degree_type_name": "学术型硕士",
        "is_statistic_direction": 1,
        "plan_id": 1191049,
        "exam_class_name": "统考",
        "remark": "招生人数为专业招生总数，非方向人数"
      },
      {
        "spe_id": 20137,
        "year": 2025,
        "depart_id": 15746,
        "special_code": "050100",
        "special_name": "中国语言文学",
        "recruit_type_name": "全日制",
        "depart_name": "人文社会科学高等研究院",
        "exam_class": 1,
        "degree_type": 2,
        "research_area": "（02）文艺学",
        "exam_subject": "①(101)思想政治理论<br/>②(201)英语（一）<br/>③(633)语言文学综合<br/>④(880)写作<br/>",
        "recruit_number": 2,
        "degree_type_name": "学术型硕士",
        "is_statistic_direction": 1,
        "plan_id": 1201424,
        "exam_class_name": "统考",
        "remark": "招生人数为专业招生总数，非方向人数"
      },
      {
        "spe_id": 20137,
        "year": 2025,
        "depart_id": 15746,
        "special_code": "050100",
        "special_name": "中国语言文学",
        "recruit_type_name": "全日制",
        "depart_name": "人文社会科学高等研究院",
        "exam_class": 1,
        "degree_type": 2,
        "research_area": "（09）汉语言文字学",
        "exam_subject": "①(101)思想政治理论<br/>②(201)英语（一）<br/>③(633)语言文学综合<br/>④(880)写作<br/>",
        "recruit_number": 2,
        "degree_type_name": "学术型硕士",
        "is_statistic_direction": 1,
        "plan_id": 1215398,
        "exam_class_name": "统考",
        "remark": "招生人数为专业招生总数，非方向人数"
      },
      {
        "spe_id": 20137,
        "year": 2025,
        "depart_id": 15746,
        "special_code": "050100",
        "special_name": "中国语言文学",
        "recruit_type_name": "全日制",
        "depart_name": "人文社会科学高等研究院",
        "exam_class": 1,
        "degree_type": 2,
        "research_area": "（05）中文创意写作",
        "exam_subject": "①(101)思想政治理论<br/>②(201)英语（一）<br/>③(633)语言文学综合<br/>④(880)写作<br/>",
        "recruit_number": 2,
        "degree_type_name": "学术型硕士",
        "is_statistic_direction": 1,
        "plan_id": 1219917,
        "exam_class_name": "统考",
        "remark": "招生人数为专业招生总数，非方向人数"
      },
      {
        "spe_id": 20137,
        "year": 2025,
        "depart_id": 15746,
        "special_code": "050100",
        "special_name": "中国语言文学",
        "recruit_type_name": "全日制",
        "depart_name": "人文社会科学高等研究院",
        "exam_class": 1,
        "degree_type": 2,
        "research_area": "（08）理论语言学",
        "exam_subject": "①(101)思想政治理论<br/>②(201)英语（一）<br/>③(633)语言文学综合<br/>④(880)写作<br/>",
        "recruit_number": 2,
        "degree_type_name": "学术型硕士",
        "is_statistic_direction": 1,
        "plan_id": 1228429,
        "exam_class_name": "统考",
        "remark": "招生人数为专业招生总数，非方向人数"
      },
      {
        "spe_id": 20188,
        "year": 2025,
        "depart_id": 15746,
        "special_code": "060200",
        "special_name": "中国史",
        "recruit_type_name": "全日制",
        "depart_name": "人文社会科学高等研究院",
        "exam_class": 1,
        "degree_type": 2,
        "research_area": "（01）.中国古代史",
        "exam_subject": "①(101)思想政治理论<br/>②(201)英语（一）<br/>③(313)历史学专业基础<br/>④(--)无<br/>",
        "recruit_number": 1,
        "degree_type_name": "学术型硕士",
        "is_statistic_direction": 1,
        "plan_id": 1140308,
        "exam_class_name": "统考",
        "remark": "招生人数为专业招生总数，非方向人数"
      },
      {
        "spe_id": 20188,
        "year": 2025,
        "depart_id": 15746,
        "special_code": "060200",
        "special_name": "中国史",
        "recruit_type_name": "全日制",
        "depart_name": "人文社会科学高等研究院",
        "exam_class": 1,
        "degree_type": 2,
        "research_area": "（03）.专门史",
        "exam_subject": "①(101)思想政治理论<br/>②(201)英语（一）<br/>③(313)历史学专业基础<br/>④(--)无<br/>",
        "recruit_number": 1,
        "degree_type_name": "学术型硕士",
        "is_statistic_direction": 1,
        "plan_id": 1153983,
        "exam_class_name": "统考",
        "remark": "招生人数为专业招生总数，非方向人数"
      },
      {
        "spe_id": 20188,
        "year": 2025,
        "depart_id": 15746,
        "special_code": "060200",
        "special_name": "中国史",
        "recruit_type_name": "全日制",
        "depart_name": "人文社会科学高等研究院",
        "exam_class": 1,
        "degree_type": 2,
        "research_area": "（02）.中国近现代史",
        "exam_subject": "①(101)思想政治理论<br/>②(201)英语（一）<br/>③(313)历史学专业基础<br/>④(--)无<br/>",
        "recruit_number": 1,
        "degree_type_name": "学术型硕士",
        "is_statistic_direction": 1,
        "plan_id": 1164267,
        "exam_class_name": "统考",
        "remark": "招生人数为专业招生总数，非方向人数"
      },
      {
        "spe_id": 20081,
        "year": 2025,
        "depart_id": 15747,
        "special_code": "035200",
        "special_name": "社会工作",
        "recruit_type_name": "全日制",
        "depart_name": "公共管理学院",
        "exam_class": 1,
        "degree_type": 1,
        "research_area": "（01）智慧社会治理与社会工作",
        "exam_subject": "①(101)思想政治理论<br/>②(204)英语（二）<br/>③(331)社会工作原理<br/>④(437)社会工作实务<br/>",
        "recruit_number": 16,
        "degree_type_name": "专业型硕士",
        "is_statistic_direction": 1,
        "plan_id": 1203130,
        "exam_class_name": "统考",
        "remark": "招生人数为专业招生总数，非方向人数"
      },
      {
        "spe_id": 20081,
        "year": 2025,
        "depart_id": 15747,
        "special_code": "035200",
        "special_name": "社会工作",
        "recruit_type_name": "全日制",
        "depart_name": "公共管理学院",
        "exam_class": 1,
        "degree_type": 1,
        "research_area": "（02）公益慈善与社区社会工作",
        "exam_subject": "①(101)思想政治理论<br/>②(204)英语（二）<br/>③(331)社会工作原理<br/>④(437)社会工作实务<br/>",
        "recruit_number": 16,
        "degree_type_name": "专业型硕士",
        "is_statistic_direction": 1,
        "plan_id": 1208637,
        "exam_class_name": "统考",
        "remark": "招生人数为专业招生总数，非方向人数"
      },
      {
        "spe_id": 20081,
        "year": 2025,
        "depart_id": 15747,
        "special_code": "035200",
        "special_name": "社会工作",
        "recruit_type_name": "全日制",
        "depart_name": "公共管理学院",
        "exam_class": 1,
        "degree_type": 1,
        "research_area": "（03）健康社会工作",
        "exam_subject": "①(101)思想政治理论<br/>②(204)英语（二）<br/>③(331)社会工作原理<br/>④(437)社会工作实务<br/>",
        "recruit_number": 16,
        "degree_type_name": "专业型硕士",
        "is_statistic_direction": 1,
        "plan_id": 1237311,
        "exam_class_name": "统考",
        "remark": "招生人数为专业招生总数，非方向人数"
      },
      {
        "spe_id": 20738,
        "year": 2025,
        "depart_id": 15747,
        "special_code": "120400",
        "special_name": "公共管理学",
        "recruit_type_name": "全日制",
        "depart_name": "公共管理学院",
        "exam_class": 1,
        "degree_type": 2,
        "research_area": "（02）公共人力资源与社会保障",
        "exam_subject": "①(101)思想政治理论<br/>②(201)英语（一）<br/>③(303)数学（三）<br/>④(803)综合考试<br/>",
        "recruit_number": 22,
        "degree_type_name": "学术型硕士",
        "is_statistic_direction": 1,
        "plan_id": 1146062,
        "exam_class_name": "统考",
        "remark": "招生人数为专业招生总数，非方向人数"
      },
      {
        "spe_id": 20738,
        "year": 2025,
        "depart_id": 15747,
        "special_code": "120400",
        "special_name": "公共管理学",
        "recruit_type_name": "全日制",
        "depart_name": "公共管理学院",
        "exam_class": 1,
        "degree_type": 2,
        "research_area": "（03）土地资源与城市管理",
        "exam_subject": "①(101)思想政治理论<br/>②(201)英语（一）<br/>③(303)数学（三）<br/>④(803)综合考试<br/>",
        "recruit_number": 22,
        "degree_type_name": "学术型硕士",
        "is_statistic_direction": 1,
        "plan_id": 1172746,
        "exam_class_name": "统考",
        "remark": "招生人数为专业招生总数，非方向人数"
      },
      {
        "spe_id": 20738,
        "year": 2025,
        "depart_id": 15747,
        "special_code": "120400",
        "special_name": "公共管理学",
        "recruit_type_name": "全日制",
        "depart_name": "公共管理学院",
        "exam_class": 1,
        "degree_type": 2,
        "research_area": "（04）公共经济与公共政策",
        "exam_subject": "①(101)思想政治理论<br/>②(201)英语（一）<br/>③(303)数学（三）<br/>④(803)综合考试<br/>",
        "recruit_number": 22,
        "degree_type_name": "学术型硕士",
        "is_statistic_direction": 1,
        "plan_id": 1175143,
        "exam_class_name": "统考",
        "remark": "招生人数为专业招生总数，非方向人数"
      },
      {
        "spe_id": 20738,
        "year": 2025,
        "depart_id": 15747,
        "special_code": "120400",
        "special_name": "公共管理学",
        "recruit_type_name": "全日制",
        "depart_name": "公共管理学院",
        "exam_class": 1,
        "degree_type": 2,
        "research_area": "（01）公共行政与政府治理",
        "exam_subject": "①(101)思想政治理论<br/>②(201)英语（一）<br/>③(303)数学（三）<br/>④(803)综合考试<br/>",
        "recruit_number": 22,
        "degree_type_name": "学术型硕士",
        "is_statistic_direction": 1,
        "plan_id": 1261704,
        "exam_class_name": "统考",
        "remark": "招生人数为专业招生总数，非方向人数"
      },
      {
        "spe_id": 20749,
        "year": 2025,
        "depart_id": 15747,
        "special_code": "125200",
        "special_name": "公共管理",
        "recruit_type_name": "非全日制",
        "depart_name": "公共管理学院",
        "exam_class": 1,
        "degree_type": 1,
        "research_area": "（00）入校后确定研究方向",
        "exam_subject": "①(199)管理类综合能力<br/>②(204)英语（二）<br/>③(-)无<br/>④(--)无<br/>",
        "recruit_number": 300,
        "degree_type_name": "专业型硕士",
        "is_statistic_direction": 1,
        "plan_id": 1214059,
        "exam_class_name": "统考",
        "remark": "招生人数为专业招生总数，非方向人数"
      },
      {
        "spe_id": 22081,
        "year": 2025,
        "depart_id": 15747,
        "special_code": "1204Z1",
        "special_name": "应急管理",
        "recruit_type_name": "全日制",
        "depart_name": "公共管理学院",
        "exam_class": 1,
        "degree_type": 2,
        "research_area": "（01）区域安全",
        "exam_subject": "①(101)思想政治理论<br/>②(201)英语（一）<br/>③(303)数学（三）<br/>④(803)综合考试<br/>",
        "recruit_number": 1,
        "degree_type_name": "学术型硕士",
        "is_statistic_direction": 1,
        "plan_id": 1160352,
        "exam_class_name": "统考",
        "remark": "招生人数为专业招生总数，非方向人数"
      },
      {
        "spe_id": 22081,
        "year": 2025,
        "depart_id": 15747,
        "special_code": "1204Z1",
        "special_name": "应急管理",
        "recruit_type_name": "全日制",
        "depart_name": "公共管理学院",
        "exam_class": 1,
        "degree_type": 2,
        "research_area": "（03）社会风险管理与政策",
        "exam_subject": "①(101)思想政治理论<br/>②(201)英语（一）<br/>③(303)数学（三）<br/>④(803)综合考试<br/>",
        "recruit_number": 1,
        "degree_type_name": "学术型硕士",
        "is_statistic_direction": 1,
        "plan_id": 1169413,
        "exam_class_name": "统考",
        "remark": "招生人数为专业招生总数，非方向人数"
      },
      {
        "spe_id": 22081,
        "year": 2025,
        "depart_id": 15747,
        "special_code": "1204Z1",
        "special_name": "应急管理",
        "recruit_type_name": "全日制",
        "depart_name": "公共管理学院",
        "exam_class": 1,
        "degree_type": 2,
        "research_area": "（02）灾害应急管理",
        "exam_subject": "①(101)思想政治理论<br/>②(201)英语（一）<br/>③(303)数学（三）<br/>④(803)综合考试<br/>",
        "recruit_number": 1,
        "degree_type_name": "学术型硕士",
        "is_statistic_direction": 1,
        "plan_id": 1207216,
        "exam_class_name": "统考",
        "remark": "招生人数为专业招生总数，非方向人数"
      },
      {
        "spe_id": 20018,
        "year": 2025,
        "depart_id": 15748,
        "special_code": "020200",
        "special_name": "应用经济学",
        "recruit_type_name": "全日制",
        "depart_name": "经济与工商管理学院",
        "exam_class": 1,
        "degree_type": 2,
        "research_area": "（04）区域经济学",
        "exam_subject": "①(101)思想政治理论<br/>②(201)英语（一）<br/>③(303)数学（三）<br/>④(804)微观经济学(含宏观经济学）<br/>",
        "recruit_number": 16,
        "degree_type_name": "学术型硕士",
        "is_statistic_direction": 1,
        "plan_id": 1185008,
        "exam_class_name": "统考",
        "remark": "招生人数为专业招生总数，非方向人数"
      },
      {
        "spe_id": 20018,
        "year": 2025,
        "depart_id": 15748,
        "special_code": "020200",
        "special_name": "应用经济学",
        "recruit_type_name": "全日制",
        "depart_name": "经济与工商管理学院",
        "exam_class": 1,
        "degree_type": 2,
        "research_area": "（03）数量经济学",
        "exam_subject": "①(101)思想政治理论<br/>②(201)英语（一）<br/>③(303)数学（三）<br/>④(804)微观经济学(含宏观经济学）<br/>",
        "recruit_number": 16,
        "degree_type_name": "学术型硕士",
        "is_statistic_direction": 1,
        "plan_id": 1216588,
        "exam_class_name": "统考",
        "remark": "招生人数为专业招生总数，非方向人数"
      },
      {
        "spe_id": 20018,
        "year": 2025,
        "depart_id": 15748,
        "special_code": "020200",
        "special_name": "应用经济学",
        "recruit_type_name": "全日制",
        "depart_name": "经济与工商管理学院",
        "exam_class": 1,
        "degree_type": 2,
        "research_area": "（02）产业经济学",
        "exam_subject": "①(101)思想政治理论<br/>②(201)英语（一）<br/>③(303)数学（三）<br/>④(804)微观经济学(含宏观经济学）<br/>",
        "recruit_number": 16,
        "degree_type_name": "学术型硕士",
        "is_statistic_direction": 1,
        "plan_id": 1221321,
        "exam_class_name": "统考",
        "remark": "招生人数为专业招生总数，非方向人数"
      }
    ]
  },
  "message": "success"
}